MANIFEST.in
README.md
setup.py
hazinses/__init__.py
hazinses/admin.py
hazinses/models.py
hazinses/tasks.py
hazinses/urls.py
hazinses/views.py
hazinses.egg-info/PKG-INFO
hazinses.egg-info/SOURCES.txt
hazinses.egg-info/dependency_links.txt
hazinses.egg-info/requires.txt
hazinses.egg-info/top_level.txt