Metadata-Version: 1.0
Name: hazinses
Version: 0.2
Summary: A simple Django app for connecting AMAZON SES-CELERY AND BOTO.
Home-page: UNKNOWN
Author: Tuna VARGI
Author-email: tunavargi@gmail.com
License: BSD License
Platform: UNKNOWN
Classifier: Environment :: Web Environment
Classifier: Framework :: Django
Classifier: Intended Audience :: Developers
Classifier: License :: OSI Approved :: BSD License
Classifier: Operating System :: OS Independent
Classifier: Programming Language :: Python
Classifier: Programming Language :: Python :: 2
Classifier: Programming Language :: Python :: 2.7
Classifier: Topic :: Internet :: WWW/HTTP
Classifier: Topic :: Internet :: WWW/HTTP :: Dynamic Content
